fadeaway/__init__.py
fadeaway/app.py
fadeaway/blueprint.py
fadeaway/config.py
fadeaway/context.py
fadeaway/exceptions.py
fadeaway/globals.py
fadeaway/middleware.py
fadeaway/response.py
fadeaway-1.0.1.dist-info/LICENSE
fadeaway-1.0.1.dist-info/METADATA
fadeaway-1.0.1.dist-info/WHEEL
fadeaway-1.0.1.dist-info/top_level.txt
fadeaway-1.0.1.dist-info/RECORD
